SkyTools/SkyTools.py
SkyTools/__init__.py
skytools_skygen-1.4.0.dist-info/METADATA
skytools_skygen-1.4.0.dist-info/WHEEL
skytools_skygen-1.4.0.dist-info/top_level.txt
skytools_skygen-1.4.0.dist-info/RECORD
