Metadata-Version: 2.1
Name: skytools-skygen
Version: 1.4.0
Summary: Easily create softwares in Python.
Home-page: https://github.com/SkyGenProg/SkyTools
Author: SkyGen
Author-email: skygen@alwaysdata.net
License: UNKNOWN
Platform: UNKNOWN
Classifier: Programming Language :: Python :: 3
Classifier: Operating System :: OS Independent
